{
  "Cities": [
    {
      "Name": "Aachen",
      "Stations": [
        {
          "Name": "Aachen Hauptbahnhof",
          "Number": 0,
          "NumberOfLapsToStop": 0,
          "Arrival": null,
          "Departure": null,
          "Track": 1,
          "IsExitOnLeft": false,
          "Flow": null,
          "Platforms": []
        }
      ]
    },
    {
      "Name": "Aschaffenburg",
      "Stations": [
        {
          "Name": "Aschaffenburg Hauptbahnhof",
          "Number": 0,
          "NumberOfLapsToStop": 0,
          "Arrival": null,
          "Departure": null,
          "Track": 1,
          "IsExitOnLeft": false,
          "Flow": null,
          "Platforms": []
        }
      ]
    },
    {
      "Name": "Augsburg",
      "Stations": [
        {
          "Name": "Augsburg Hauptbahnhof",
          "Number": 0,
          "NumberOfLapsToStop": 0,
          "Arrival": null,
          "Departure": null,
          "Track": 1,
          "IsExitOnLeft": false,
          "Flow": null,
          "Platforms": []
        }
      ]
    },
    {
      "Name": "Bad Oeynhausen",
      "Stations": [
        {
          "Name": "Bad Oeynhausen Bahnhof",
          "Number": 0,
          "NumberOfLapsToStop": 0,
          "Arrival": null,
          "Departure": null,
          "Track": 1,
          "IsExitOnLeft": false,
          "Flow": null,
          "Platforms": []
        }
      ]
    },
    {
      "Name": "Bamberg",
      "Stations": [
        {
          "Name": "Bamberg Bahnhof",
          "Number": 0,
          "NumberOfLapsToStop": 0,
          "Arrival": null,
          "Departure": null,
          "Track": 1,
          "IsExitOnLeft": false,
          "Flow": null,
          "Platforms": []
        }
      ]
    },
    {
      "Name": "Berlin",
      "Stations": [
        {
          "Name": "Berlin Hauptbahnhof",
          "Number": 0,
          "NumberOfLapsToStop": 0,
          "Arrival": null,
          "Departure": null,
          "Track": 1,
          "IsExitOnLeft": false,
          "Flow": null,
          "Platforms": []
        }
      ]
    },
    {
      "Name": "Bielefeld",
      "Stations": [
        {
          "Name": "Bielefeld Hauptbahnhof",
          "Number": 0,
          "NumberOfLapsToStop": 0,
          "Arrival": null,
          "Departure": null,
          "Track": 1,
          "IsExitOnLeft": false,
          "Flow": null,
          "Platforms": []
        }
      ]
    },
    {
      "Name": "Bochum",
      "Stations": [
        {
          "Name": "Bochum Hauptbahnhof",
          "Number": 0,
          "NumberOfLapsToStop": 0,
          "Arrival": null,
          "Departure": null,
          "Track": 1,
          "IsExitOnLeft": false,
          "Flow": null,
          "Platforms": []
        }
      ]
    },
    {
      "Name": "Bonn",
      "Stations": [
        {
          "Name": "Bonn Hauptbahnhof",
          "Number": 0,
          "NumberOfLapsToStop": 0,
          "Arrival": null,
          "Departure": null,
          "Track": 1,
          "IsExitOnLeft": false,
          "Flow": null,
          "Platforms": []
        }
      ]
    },
    {
      "Name": "Bottrop",
      "Stations": [
        {
          "Name": "Bottrop Hauptbahnhof",
          "Number": 0,
          "NumberOfLapsToStop": 0,
          "Arrival": null,
          "Departure": null,
          "Track": 1,
          "IsExitOnLeft": false,
          "Flow": null,
          "Platforms": []
        }
      ]
    },
    {
      "Name": "Braunschweig",
      "Stations": [
        {
          "Name": "Braunschweig Hauptbahnhof",
          "Number": 0,
          "NumberOfLapsToStop": 0,
          "Arrival": null,
          "Departure": null,
          "Track": 1,
          "IsExitOnLeft": false,
          "Flow": null,
          "Platforms": []
        }
      ]
    },
    {
      "Name": "Bremen",
      "Stations": [
        {
          "Name": "Bremen Hauptbahnhof",
          "Number": 0,
          "NumberOfLapsToStop": 0,
          "Arrival": null,
          "Departure": null,
          "Track": 1,
          "IsExitOnLeft": false,
          "Flow": null,
          "Platforms": []
        }
      ]
    },
    {
      "Name": "Bremerhaven",
      "Stations": [
        {
          "Name": "Bremerhaven Hauptbahnhof",
          "Number": 0,
          "NumberOfLapsToStop": 0,
          "Arrival": null,
          "Departure": null,
          "Track": 1,
          "IsExitOnLeft": false,
          "Flow": null,
          "Platforms": []
        }
      ]
    },
    {
      "Name": "Chemnitz",
      "Stations": [
        {
          "Name": "Chemnitz Hauptbahnhof",
          "Number": 0,
          "NumberOfLapsToStop": 0,
          "Arrival": null,
          "Departure": null,
          "Track": 1,
          "IsExitOnLeft": false,
          "Flow": null,
          "Platforms": []
        }
      ]
    },
    {
      "Name": "Cottbus",
      "Stations": [
        {
          "Name": "Cottbus Hauptbahnhof",
          "Number": 0,
          "NumberOfLapsToStop": 0,
          "Arrival": null,
          "Departure": null,
          "Track": 1,
          "IsExitOnLeft": false,
          "Flow": null,
          "Platforms": []
        }
      ]
    },
    {
      "Name": "Darmstadt",
      "Stations": [
        {
          "Name": "Darmstadt Hauptbahnhof",
          "Number": 0,
          "NumberOfLapsToStop": 0,
          "Arrival": null,
          "Departure": null,
          "Track": 1,
          "IsExitOnLeft": false,
          "Flow": null,
          "Platforms": []
        }
      ]
    },
    {
      "Name": "Detmold",
      "Stations": [
        {
          "Name": "Detmold Bahnhof",
          "Number": 0,
          "NumberOfLapsToStop": 0,
          "Arrival": null,
          "Departure": null,
          "Track": 1,
          "IsExitOnLeft": false,
          "Flow": null,
          "Platforms": []
        }
      ]
    },
    {
      "Name": "Dortmund",
      "Stations": [
        {
          "Name": "Dortmund Hauptbahnhof",
          "Number": 0,
          "NumberOfLapsToStop": 0,
          "Arrival": null,
          "Departure": null,
          "Track": 1,
          "IsExitOnLeft": false,
          "Flow": null,
          "Platforms": []
        }
      ]
    },
    {
      "Name": "Dresden",
      "Stations": [
        {
          "Name": "Dresden Hauptbahnhof",
          "Number": 0,
          "NumberOfLapsToStop": 0,
          "Arrival": null,
          "Departure": null,
          "Track": 1,
          "IsExitOnLeft": false,
          "Flow": null,
          "Platforms": []
        }
      ]
    },
    {
      "Name": "Duisburg",
      "Stations": [
        {
          "Name": "Duisburg Hauptbahnhof",
          "Number": 0,
          "NumberOfLapsToStop": 0,
          "Arrival": null,
          "Departure": null,
          "Track": 1,
          "IsExitOnLeft": false,
          "Flow": null,
          "Platforms": []
        }
      ]
    },
    {
      "Name": "Düsseldorf",
      "Stations": [
        {
          "Name": "Düsseldorf Hauptbahnhof",
          "Number": 0,
          "NumberOfLapsToStop": 0,
          "Arrival": null,
          "Departure": null,
          "Track": 1,
          "IsExitOnLeft": false,
          "Flow": null,
          "Platforms": []
        }
      ]
    },
    {
      "Name": "Erfurt",
      "Stations": [
        {
          "Name": "Erfurt Hauptbahnhof",
          "Number": 0,
          "NumberOfLapsToStop": 0,
          "Arrival": null,
          "Departure": null,
          "Track": 1,
          "IsExitOnLeft": false,
          "Flow": null,
          "Platforms": []
        }
      ]
    },
    {
      "Name": "Erlangen",
      "Stations": [
        {
          "Name": "Erlangen Bahnhof",
          "Number": 0,
          "NumberOfLapsToStop": 0,
          "Arrival": null,
          "Departure": null,
          "Track": 1,
          "IsExitOnLeft": false,
          "Flow": null,
          "Platforms": []
        }
      ]
    },
    {
      "Name": "Essen",
      "Stations": [
        {
          "Name": "Essen Hauptbahnhof",
          "Number": 0,
          "NumberOfLapsToStop": 0,
          "Arrival": null,
          "Departure": null,
          "Track": 1,
          "IsExitOnLeft": false,
          "Flow": null,
          "Platforms": []
        }
      ]
    },
    {
      "Name": "Frankfurt am Main",
      "Stations": [
        {
          "Name": "Frankfurt (Main) Hauptbahnhof",
          "Number": 0,
          "NumberOfLapsToStop": 0,
          "Arrival": null,
          "Departure": null,
          "Track": 1,
          "IsExitOnLeft": false,
          "Flow": null,
          "Platforms": []
        }
      ]
    },
    {
      "Name": "Freiburg im Breisgau",
      "Stations": [
        {
          "Name": "Freiburg (Breisgau) Hauptbahnhof",
          "Number": 0,
          "NumberOfLapsToStop": 0,
          "Arrival": null,
          "Departure": null,
          "Track": 1,
          "IsExitOnLeft": false,
          "Flow": null,
          "Platforms": []
        }
      ]
    },
    {
      "Name": "Fulda",
      "Stations": [
        {
          "Name": "Fulda Bahnhof",
          "Number": 0,
          "NumberOfLapsToStop": 0,
          "Arrival": null,
          "Departure": null,
          "Track": 1,
          "IsExitOnLeft": false,
          "Flow": null,
          "Platforms": []
        }
      ]
    },
    {
      "Name": "Fürth",
      "Stations": [
        {
          "Name": "Fürth Hauptbahnhof",
          "Number": 0,
          "NumberOfLapsToStop": 0,
          "Arrival": null,
          "Departure": null,
          "Track": 1,
          "IsExitOnLeft": false,
          "Flow": null,
          "Platforms": []
        }
      ]
    },
    {
      "Name": "Gelsenkirchen",
      "Stations": [
        {
          "Name": "Gelsenkirchen Hauptbahnhof",
          "Number": 0,
          "NumberOfLapsToStop": 0,
          "Arrival": null,
          "Departure": null,
          "Track": 1,
          "IsExitOnLeft": false,
          "Flow": null,
          "Platforms": []
        }
      ]
    },
    {
      "Name": "Gießen",
      "Stations": [
        {
          "Name": "Gießen Bahnhof",
          "Number": 0,
          "NumberOfLapsToStop": 0,
          "Arrival": null,
          "Departure": null,
          "Track": 1,
          "IsExitOnLeft": false,
          "Flow": null,
          "Platforms": []
        }
      ]
    },
    {
      "Name": "Gütersloh",
      "Stations": [
        {
          "Name": "Gütersloh Hauptbahnhof",
          "Number": 0,
          "NumberOfLapsToStop": 0,
          "Arrival": null,
          "Departure": null,
          "Track": 1,
          "IsExitOnLeft": false,
          "Flow": null,
          "Platforms": []
        }
      ]
    },
    {
      "Name": "Göttingen",
      "Stations": [
        {
          "Name": "Göttingen Bahnhof",
          "Number": 0,
          "NumberOfLapsToStop": 0,
          "Arrival": null,
          "Departure": null,
          "Track": 1,
          "IsExitOnLeft": false,
          "Flow": null,
          "Platforms": []
        }
      ]
    },
    {
      "Name": "Hagen",
      "Stations": [
        {
          "Name": "Hagen Hauptbahnhof",
          "Number": 0,
          "NumberOfLapsToStop": 0,
          "Arrival": null,
          "Departure": null,
          "Track": 1,
          "IsExitOnLeft": false,
          "Flow": null,
          "Platforms": []
        }
      ]
    },
    {
      "Name": "Halle (Saale)",
      "Stations": [
        {
          "Name": "Halle (Saale) Hauptbahnhof",
          "Number": 0,
          "NumberOfLapsToStop": 0,
          "Arrival": null,
          "Departure": null,
          "Track": 1,
          "IsExitOnLeft": false,
          "Flow": null,
          "Platforms": []
        }
      ]
    },
    {
      "Name": "Hamburg",
      "Stations": [
        {
          "Name": "Hamburg Hauptbahnhof",
          "Number": 0,
          "NumberOfLapsToStop": 0,
          "Arrival": null,
          "Departure": null,
          "Track": 1,
          "IsExitOnLeft": false,
          "Flow": null,
          "Platforms": []
        }
      ]
    },
    {
      "Name": "Hamm",
      "Stations": [
        {
          "Name": "Hamm (Westf) Hauptbahnhof",
          "Number": 0,
          "NumberOfLapsToStop": 0,
          "Arrival": null,
          "Departure": null,
          "Track": 1,
          "IsExitOnLeft": false,
          "Flow": null,
          "Platforms": []
        }
      ]
    },
    {
      "Name": "Hannover",
      "Stations": [
        {
          "Name": "Hannover Hauptbahnhof",
          "Number": 0,
          "NumberOfLapsToStop": 0,
          "Arrival": null,
          "Departure": null,
          "Track": 1,
          "IsExitOnLeft": false,
          "Flow": null,
          "Platforms": []
        }
      ]
    },
    {
      "Name": "Heidelberg",
      "Stations": [
        {
          "Name": "Heidelberg Hauptbahnhof",
          "Number": 0,
          "NumberOfLapsToStop": 0,
          "Arrival": null,
          "Departure": null,
          "Track": 1,
          "IsExitOnLeft": false,
          "Flow": null,
          "Platforms": []
        }
      ]
    },
    {
      "Name": "Heilbronn",
      "Stations": [
        {
          "Name": "Heilbronn Hauptbahnhof",
          "Number": 0,
          "NumberOfLapsToStop": 0,
          "Arrival": null,
          "Departure": null,
          "Track": 1,
          "IsExitOnLeft": false,
          "Flow": null,
          "Platforms": []
        }
      ]
    },
    {
      "Name": "Herford",
      "Stations": [
        {
          "Name": "Herford Bahnhof",
          "Number": 0,
          "NumberOfLapsToStop": 0,
          "Arrival": null,
          "Departure": null,
          "Track": 1,
          "IsExitOnLeft": false,
          "Flow": null,
          "Platforms": []
        }
      ]
    },
    {
      "Name": "Hildesheim",
      "Stations": [
        {
          "Name": "Hildesheim Hauptbahnhof",
          "Number": 0,
          "NumberOfLapsToStop": 0,
          "Arrival": null,
          "Departure": null,
          "Track": 1,
          "IsExitOnLeft": false,
          "Flow": null,
          "Platforms": []
        }
      ]
    },
    {
      "Name": "Ingolstadt",
      "Stations": [
        {
          "Name": "Ingolstadt Hauptbahnhof",
          "Number": 0,
          "NumberOfLapsToStop": 0,
          "Arrival": null,
          "Departure": null,
          "Track": 1,
          "IsExitOnLeft": false,
          "Flow": null,
          "Platforms": []
        }
      ]
    },
    {
      "Name": "Jena",
      "Stations": [
        {
          "Name": "Jena Paradies",
          "Number": 0,
          "NumberOfLapsToStop": 0,
          "Arrival": null,
          "Departure": null,
          "Track": 1,
          "IsExitOnLeft": false,
          "Flow": null,
          "Platforms": []
        }
      ]
    },
    {
      "Name": "Karlsruhe",
      "Stations": [
        {
          "Name": "Karlsruhe Hauptbahnhof",
          "Number": 0,
          "NumberOfLapsToStop": 0,
          "Arrival": null,
          "Departure": null,
          "Track": 1,
          "IsExitOnLeft": false,
          "Flow": null,
          "Platforms": []
        }
      ]
    },
    {
      "Name": "Kassel",
      "Stations": [
        {
          "Name": "Kassel-Wilhelmshöhe",
          "Number": 0,
          "NumberOfLapsToStop": 0,
          "Arrival": null,
          "Departure": null,
          "Track": 1,
          "IsExitOnLeft": false,
          "Flow": null,
          "Platforms": []
        }
      ]
    },
    {
      "Name": "Kiel",
      "Stations": [
        {
          "Name": "Kiel Hauptbahnhof",
          "Number": 0,
          "NumberOfLapsToStop": 0,
          "Arrival": null,
          "Departure": null,
          "Track": 1,
          "IsExitOnLeft": false,
          "Flow": null,
          "Platforms": []
        }
      ]
    },
    {
      "Name": "Koblenz",
      "Stations": [
        {
          "Name": "Koblenz Hauptbahnhof",
          "Number": 0,
          "NumberOfLapsToStop": 0,
          "Arrival": null,
          "Departure": null,
          "Track": 1,
          "IsExitOnLeft": false,
          "Flow": null,
          "Platforms": []
        }
      ]
    },
    {
      "Name": "Köln",
      "Stations": [
        {
          "Name": "Köln Hauptbahnhof",
          "Number": 0,
          "NumberOfLapsToStop": 0,
          "Arrival": null,
          "Departure": null,
          "Track": 1,
          "IsExitOnLeft": false,
          "Flow": null,
          "Platforms": []
        }
      ]
    },
    {
      "Name": "Konstanz",
      "Stations": [
        {
          "Name": "Konstanz Bahnhof",
          "Number": 0,
          "NumberOfLapsToStop": 0,
          "Arrival": null,
          "Departure": null,
          "Track": 1,
          "IsExitOnLeft": false,
          "Flow": null,
          "Platforms": []
        }
      ]
    },
    {
      "Name": "Krefeld",
      "Stations": [
        {
          "Name": "Krefeld Hauptbahnhof",
          "Number": 0,
          "NumberOfLapsToStop": 0,
          "Arrival": null,
          "Departure": null,
          "Track": 1,
          "IsExitOnLeft": false,
          "Flow": null,
          "Platforms": []
        }
      ]
    },
    {
      "Name": "Leipzig",
      "Stations": [
        {
          "Name": "Leipzig Hauptbahnhof",
          "Number": 0,
          "NumberOfLapsToStop": 0,
          "Arrival": null,
          "Departure": null,
          "Track": 1,
          "IsExitOnLeft": false,
          "Flow": null,
          "Platforms": []
        }
      ]
    },
    {
      "Name": "Leverkusen",
      "Stations": [
        {
          "Name": "Leverkusen Mitte",
          "Number": 0,
          "NumberOfLapsToStop": 0,
          "Arrival": null,
          "Departure": null,
          "Track": 1,
          "IsExitOnLeft": false,
          "Flow": null,
          "Platforms": []
        }
      ]
    },
    {
      "Name": "Lübeck",
      "Stations": [
        {
          "Name": "Lübeck Hauptbahnhof",
          "Number": 0,
          "NumberOfLapsToStop": 0,
          "Arrival": null,
          "Departure": null,
          "Track": 1,
          "IsExitOnLeft": false,
          "Flow": null,
          "Platforms": []
        }
      ]
    },
    {
      "Name": "Ludwigshafen am Rhein",
      "Stations": [
        {
          "Name": "Ludwigshafen (Rhein) Hauptbahnhof",
          "Number": 0,
          "NumberOfLapsToStop": 0,
          "Arrival": null,
          "Departure": null,
          "Track": 1,
          "IsExitOnLeft": false,
          "Flow": null,
          "Platforms": []
        }
      ]
    },
    {
      "Name": "Lüneburg",
      "Stations": [
        {
          "Name": "Lüneburg Bahnhof",
          "Number": 0,
          "NumberOfLapsToStop": 0,
          "Arrival": null,
          "Departure": null,
          "Track": 1,
          "IsExitOnLeft": false,
          "Flow": null,
          "Platforms": []
        }
      ]
    },
    {
      "Name": "Magdeburg",
      "Stations": [
        {
          "Name": "Magdeburg Hauptbahnhof",
          "Number": 0,
          "NumberOfLapsToStop": 0,
          "Arrival": null,
          "Departure": null,
          "Track": 1,
          "IsExitOnLeft": false,
          "Flow": null,
          "Platforms": []
        }
      ]
    },
    {
      "Name": "Mainz",
      "Stations": [
        {
          "Name": "Mainz Hauptbahnhof",
          "Number": 0,
          "NumberOfLapsToStop": 0,
          "Arrival": null,
          "Departure": null,
          "Track": 1,
          "IsExitOnLeft": false,
          "Flow": null,
          "Platforms": []
        }
      ]
    },
    {
      "Name": "Mannheim",
      "Stations": [
        {
          "Name": "Mannheim Hauptbahnhof",
          "Number": 0,
          "NumberOfLapsToStop": 0,
          "Arrival": null,
          "Departure": null,
          "Track": 1,
          "IsExitOnLeft": false,
          "Flow": null,
          "Platforms": []
        }
      ]
    },
    {
      "Name": "Marburg",
      "Stations": [
        {
          "Name": "Marburg (Lahn) Bahnhof",
          "Number": 0,
          "NumberOfLapsToStop": 0,
          "Arrival": null,
          "Departure": null,
          "Track": 1,
          "IsExitOnLeft": false,
          "Flow": null,
          "Platforms": []
        }
      ]
    },
    {
      "Name": "Minden",
      "Stations": [
        {
          "Name": "Minden (Westf) Bahnhof",
          "Number": 0,
          "NumberOfLapsToStop": 0,
          "Arrival": null,
          "Departure": null,
          "Track": 1,
          "IsExitOnLeft": false,
          "Flow": null,
          "Platforms": []
        }
      ]
    },
    {
      "Name": "Mönchengladbach",
      "Stations": [
        {
          "Name": "Mönchengladbach Hauptbahnhof",
          "Number": 0,
          "NumberOfLapsToStop": 0,
          "Arrival": null,
          "Departure": null,
          "Track": 1,
          "IsExitOnLeft": false,
          "Flow": null,
          "Platforms": []
        }
      ]
    },
    {
      "Name": "Mülheim an der Ruhr",
      "Stations": [
        {
          "Name": "Mülheim (Ruhr) Hauptbahnhof",
          "Number": 0,
          "NumberOfLapsToStop": 0,
          "Arrival": null,
          "Departure": null,
          "Track": 1,
          "IsExitOnLeft": false,
          "Flow": null,
          "Platforms": []
        }
      ]
    },
    {
      "Name": "München",
      "Stations": [
        {
          "Name": "München Hauptbahnhof",
          "Number": 0,
          "NumberOfLapsToStop": 0,
          "Arrival": null,
          "Departure": null,
          "Track": 1,
          "IsExitOnLeft": false,
          "Flow": null,
          "Platforms": []
        }
      ]
    },
    {
      "Name": "Münster",
      "Stations": [
        {
          "Name": "Münster (Westf) Hauptbahnhof",
          "Number": 0,
          "NumberOfLapsToStop": 0,
          "Arrival": null,
          "Departure": null,
          "Track": 1,
          "IsExitOnLeft": false,
          "Flow": null,
          "Platforms": []
        }
      ]
    },
    {
      "Name": "Neuss",
      "Stations": [
        {
          "Name": "Neuss Hauptbahnhof",
          "Number": 0,
          "NumberOfLapsToStop": 0,
          "Arrival": null,
          "Departure": null,
          "Track": 1,
          "IsExitOnLeft": false,
          "Flow": null,
          "Platforms": []
        }
      ]
    },
    {
      "Name": "Nürnberg",
      "Stations": [
        {
          "Name": "Nürnberg Hauptbahnhof",
          "Number": 0,
          "NumberOfLapsToStop": 0,
          "Arrival": null,
          "Departure": null,
          "Track": 1,
          "IsExitOnLeft": false,
          "Flow": null,
          "Platforms": []
        }
      ]
    },
    {
      "Name": "Oberhausen",
      "Stations": [
        {
          "Name": "Oberhausen Hauptbahnhof",
          "Number": 0,
          "NumberOfLapsToStop": 0,
          "Arrival": null,
          "Departure": null,
          "Track": 1,
          "IsExitOnLeft": false,
          "Flow": null,
          "Platforms": []
        }
      ]
    },
    {
      "Name": "Offenbach am Main",
      "Stations": [
        {
          "Name": "Offenbach (Main) Hauptbahnhof",
          "Number": 0,
          "NumberOfLapsToStop": 0,
          "Arrival": null,
          "Departure": null,
          "Track": 1,
          "IsExitOnLeft": false,
          "Flow": null,
          "Platforms": []
        }
      ]
    },
    {
      "Name": "Oldenburg",
      "Stations": [
        {
          "Name": "Oldenburg (Oldb) Hauptbahnhof",
          "Number": 0,
          "NumberOfLapsToStop": 0,
          "Arrival": null,
          "Departure": null,
          "Track": 1,
          "IsExitOnLeft": false,
          "Flow": null,
          "Platforms": []
        }
      ]
    },
    {
      "Name": "Osnabrück",
      "Stations": [
        {
          "Name": "Osnabrück Hauptbahnhof",
          "Number": 0,
          "NumberOfLapsToStop": 0,
          "Arrival": null,
          "Departure": null,
          "Track": 1,
          "IsExitOnLeft": false,
          "Flow": null,
          "Platforms": []
        }
      ]
    },
    {
      "Name": "Paderborn",
      "Stations": [
        {
          "Name": "Paderborn Hauptbahnhof",
          "Number": 0,
          "NumberOfLapsToStop": 0,
          "Arrival": null,
          "Departure": null,
          "Track": 1,
          "IsExitOnLeft": false,
          "Flow": null,
          "Platforms": []
        }
      ]
    },
    {
      "Name": "Pforzheim",
      "Stations": [
        {
          "Name": "Pforzheim Hauptbahnhof",
          "Number": 0,
          "NumberOfLapsToStop": 0,
          "Arrival": null,
          "Departure": null,
          "Track": 1,
          "IsExitOnLeft": false,
          "Flow": null,
          "Platforms": []
        }
      ]
    },
    {
      "Name": "Potsdam",
      "Stations": [
        {
          "Name": "Potsdam Hauptbahnhof",
          "Number": 0,
          "NumberOfLapsToStop": 0,
          "Arrival": null,
          "Departure": null,
          "Track": 1,
          "IsExitOnLeft": false,
          "Flow": null,
          "Platforms": []
        }
      ]
    },
    {
      "Name": "Recklinghausen",
      "Stations": [
        {
          "Name": "Recklinghausen Hauptbahnhof",
          "Number": 0,
          "NumberOfLapsToStop": 0,
          "Arrival": null,
          "Departure": null,
          "Track": 1,
          "IsExitOnLeft": false,
          "Flow": null,
          "Platforms": []
        }
      ]
    },
    {
      "Name": "Regensburg",
      "Stations": [
        {
          "Name": "Regensburg Hauptbahnhof",
          "Number": 0,
          "NumberOfLapsToStop": 0,
          "Arrival": null,
          "Departure": null,
          "Track": 1,
          "IsExitOnLeft": false,
          "Flow": null,
          "Platforms": []
        }
      ]
    },
    {
      "Name": "Remscheid",
      "Stations": [
        {
          "Name": "Remscheid Hauptbahnhof",
          "Number": 0,
          "NumberOfLapsToStop": 0,
          "Arrival": null,
          "Departure": null,
          "Track": 1,
          "IsExitOnLeft": false,
          "Flow": null,
          "Platforms": []
        }
      ]
    },
    {
      "Name": "Reutlingen",
      "Stations": [
        {
          "Name": "Reutlingen Hauptbahnhof",
          "Number": 0,
          "NumberOfLapsToStop": 0,
          "Arrival": null,
          "Departure": null,
          "Track": 1,
          "IsExitOnLeft": false,
          "Flow": null,
          "Platforms": []
        }
      ]
    },
    {
      "Name": "Rostock",
      "Stations": [
        {
          "Name": "Rostock Hauptbahnhof",
          "Number": 0,
          "NumberOfLapsToStop": 0,
          "Arrival": null,
          "Departure": null,
          "Track": 1,
          "IsExitOnLeft": false,
          "Flow": null,
          "Platforms": []
        }
      ]
    },
    {
      "Name": "Saarbrücken",
      "Stations": [
        {
          "Name": "Saarbrücken Hauptbahnhof",
          "Number": 0,
          "NumberOfLapsToStop": 0,
          "Arrival": null,
          "Departure": null,
          "Track": 1,
          "IsExitOnLeft": false,
          "Flow": null,
          "Platforms": []
        }
      ]
    },
    {
      "Name": "Salzgitter",
      "Stations": [
        {
          "Name": "Salzgitter-Bad Bahnhof",
          "Number": 0,
          "NumberOfLapsToStop": 0,
          "Arrival": null,
          "Departure": null,
          "Track": 1,
          "IsExitOnLeft": false,
          "Flow": null,
          "Platforms": []
        }
      ]
    },
    {
      "Name": "Schwerin",
      "Stations": [
        {
          "Name": "Schwerin Hauptbahnhof",
          "Number": 0,
          "NumberOfLapsToStop": 0,
          "Arrival": null,
          "Departure": null,
          "Track": 1,
          "IsExitOnLeft": false,
          "Flow": null,
          "Platforms": []
        }
      ]
    },
    {
      "Name": "Siegen",
      "Stations": [
        {
          "Name": "Siegen Hauptbahnhof",
          "Number": 0,
          "NumberOfLapsToStop": 0,
          "Arrival": null,
          "Departure": null,
          "Track": 1,
          "IsExitOnLeft": false,
          "Flow": null,
          "Platforms": []
        }
      ]
    },
    {
      "Name": "Solingen",
      "Stations": [
        {
          "Name": "Solingen Hauptbahnhof",
          "Number": 0,
          "NumberOfLapsToStop": 0,
          "Arrival": null,
          "Departure": null,
          "Track": 1,
          "IsExitOnLeft": false,
          "Flow": null,
          "Platforms": []
        }
      ]
    },
    {
      "Name": "Stuttgart",
      "Stations": [
        {
          "Name": "Stuttgart Hauptbahnhof",
          "Number": 0,
          "NumberOfLapsToStop": 0,
          "Arrival": null,
          "Departure": null,
          "Track": 1,
          "IsExitOnLeft": false,
          "Flow": null,
          "Platforms": []
        }
      ]
    },
    {
      "Name": "Trier",
      "Stations": [
        {
          "Name": "Trier Hauptbahnhof",
          "Number": 0,
          "NumberOfLapsToStop": 0,
          "Arrival": null,
          "Departure": null,
          "Track": 1,
          "IsExitOnLeft": false,
          "Flow": null,
          "Platforms": []
        }
      ]
    },
    {
      "Name": "Ulm",
      "Stations": [
        {
          "Name": "Ulm Hauptbahnhof",
          "Number": 0,
          "NumberOfLapsToStop": 0,
          "Arrival": null,
          "Departure": null,
          "Track": 1,
          "IsExitOnLeft": false,
          "Flow": null,
          "Platforms": []
        }
      ]
    },
    {
      "Name": "Wiesbaden",
      "Stations": [
        {
          "Name": "Wiesbaden Hauptbahnhof",
          "Number": 0,
          "NumberOfLapsToStop": 0,
          "Arrival": null,
          "Departure": null,
          "Track": 1,
          "IsExitOnLeft": false,
          "Flow": null,
          "Platforms": []
        }
      ]
    },
    {
      "Name": "Wilhelmshaven",
      "Stations": [
        {
          "Name": "Wilhelmshaven Hauptbahnhof",
          "Number": 0,
          "NumberOfLapsToStop": 0,
          "Arrival": null,
          "Departure": null,
          "Track": 1,
          "IsExitOnLeft": false,
          "Flow": null,
          "Platforms": []
        }
      ]
    },
    {
      "Name": "Wolfsburg",
      "Stations": [
        {
          "Name": "Wolfsburg Hauptbahnhof",
          "Number": 0,
          "NumberOfLapsToStop": 0,
          "Arrival": null,
          "Departure": null,
          "Track": 1,
          "IsExitOnLeft": false,
          "Flow": null,
          "Platforms": []
        }
      ]
    },
    {
      "Name": "Wuppertal",
      "Stations": [
        {
          "Name": "Wuppertal Hauptbahnhof",
          "Number": 0,
          "NumberOfLapsToStop": 0,
          "Arrival": null,
          "Departure": null,
          "Track": 1,
          "IsExitOnLeft": false,
          "Flow": null,
          "Platforms": []
        }
      ]
    },
    {
      "Name": "Würzburg",
      "Stations": [
        {
          "Name": "Würzburg Hauptbahnhof",
          "Number": 0,
          "NumberOfLapsToStop": 0,
          "Arrival": null,
          "Departure": null,
          "Track": 1,
          "IsExitOnLeft": false,
          "Flow": null,
          "Platforms": []
        }
      ]
    },
    {
      "Name": "Zwickau",
      "Stations": [
        {
          "Name": "Zwickau Hauptbahnhof",
          "Number": 0,
          "NumberOfLapsToStop": 0,
          "Arrival": null,
          "Departure": null,
          "Track": 1,
          "IsExitOnLeft": false,
          "Flow": null,
          "Platforms": []
        }
      ]
    }
  ]
}
